{
  "actions": [
    {
      "acted_at": "2016-09-28", 
      "action_code": "Intro-H", 
      "references": [], 
      "text": "Introduced in House", 
      "type": "action"
    }, 
    {
      "acted_at": "2016-09-28", 
      "action_code": "H11100", 
      "committees": [
        "HSVR"
      ], 
      "references": [], 
      "status": "REFERRED", 
      "text": "Referred to the House Committee on Veterans' Affairs.", 
      "type": "referral"
    }, 
    {
      "acted_at": "2016-10-19", 
      "action_code": "", 
      "committees": [
        "HSVR"
      ], 
      "references": [], 
      "text": "Referred to the Subcommittee on Health.", 
      "type": "referral"
    }
  ], 
  "amendments": [], 
  "bill_id": "hr6277-114", 
  "bill_type": "hr", 
  "by_request": false, 
  "committee_reports": [], 
  "committees": [
    {
      "activity": [
        "referral"
      ], 
      "committee": "House Veterans' Affairs", 
      "committee_id": "HSVR"
    }, 
    {
      "activity": [
        "referral"
      ], 
      "committee": "House Veterans' Affairs", 
      "committee_id": "HSVR", 
      "subcommittee": "Subcommittee on Health", 
      "subcommittee_id": "03"
    }
  ], 
  "congress": "114", 
  "cosponsors": [
    {
      "bioguide_id": "A000374", 
      "district": "5", 
      "name": "Abraham, Ralph Lee", 
      "original_cosponsor": true, 
      "sponsored_at": "2016-09-28", 
      "state": "LA", 
      "title": "Rep", 
      "withdrawn_at": null
    }, 
    {
      "bioguide_id": "B001255", 
      "district": "3", 
      "name": "Boustany, Charles W., Jr.", 
      "original_cosponsor": true, 
      "sponsored_at": "2016-09-28", 
      "state": "LA", 
      "title": "Rep", 
      "withdrawn_at": null
    }, 
    {
      "bioguide_id": "B001275", 
      "district": "8", 
      "name": "Bucshon, Larry", 
      "original_cosponsor": true, 
      "sponsored_at": "2016-09-28", 
      "state": "IN", 
      "title": "Rep", 
      "withdrawn_at": null
    }, 
    {
      "bioguide_id": "G000565", 
      "district": "4", 
      "name": "Gosar, Paul A.", 
      "original_cosponsor": false, 
      "sponsored_at": "2016-11-14", 
      "state": "AZ", 
      "title": "Rep", 
      "withdrawn_at": null
    }, 
    {
      "bioguide_id": "H001052", 
      "district": "1", 
      "name": "Harris, Andy", 
      "original_cosponsor": true, 
      "sponsored_at": "2016-09-28", 
      "state": "MD", 
      "title": "Rep", 
      "withdrawn_at": null
    }, 
    {
      "bioguide_id": "L000564", 
      "district": "5", 
      "name": "Lamborn, Doug", 
      "original_cosponsor": false, 
      "sponsored_at": "2016-11-16", 
      "state": "CO", 
      "title": "Rep", 
      "withdrawn_at": null
    }, 
    {
      "bioguide_id": "P000591", 
      "district": "6", 
      "name": "Price, Tom", 
      "original_cosponsor": true, 
      "sponsored_at": "2016-09-28", 
      "state": "GA", 
      "title": "Rep", 
      "withdrawn_at": null
    }
  ], 
  "enacted_as": null, 
  "history": {
    "active": false, 
    "awaiting_signature": false, 
    "enacted": false, 
    "vetoed": false
  }, 
  "introduced_at": "2016-09-28", 
  "number": "6277", 
  "official_title": "To prohibit the implementation of a proposed Department of Veterans Affairs rule relating to the practice authority of advanced practice registered nurses.", 
  "popular_title": null, 
  "related_bills": [], 
  "short_title": "Veterans' Health Care Safety Act of 2016", 
  "sponsor": {
    "bioguide_id": "R000582", 
    "district": "1", 
    "name": "Roe, David P.", 
    "state": "TN", 
    "title": "Rep", 
    "type": "person"
  }, 
  "status": "REFERRED", 
  "status_at": "2016-09-28", 
  "subjects": [
    "Armed forces and national security"
  ], 
  "subjects_top_term": "Armed forces and national security", 
  "summary": {
    "as": "Introduced in House", 
    "date": "2016-09-28T04:00:00Z", 
    "text": "Veterans' Health Care Safety Act of 2016\n\nThis bill prohibits implementation of a proposed Department of Veterans Affairs (VA) rule to permit full practice authority of all VA advanced practice registered nurses when they are acting within the scope of their VA employment."
  }, 
  "titles": [
    {
      "as": "introduced", 
      "is_for_portion": false, 
      "title": "Veterans' Health Care Safety Act of 2016", 
      "type": "short"
    }, 
    {
      "as": "introduced", 
      "is_for_portion": false, 
      "title": "To prohibit the implementation of a proposed Department of Veterans Affairs rule relating to the practice authority of advanced practice registered nurses.", 
      "type": "official"
    }, 
    {
      "as": null, 
      "is_for_portion": false, 
      "title": "Veterans' Health Care Safety Act of 2016", 
      "type": "display"
    }
  ], 
  "updated_at": "2018-06-02T05:32:19Z", 
  "url": "https://www.govinfo.gov/bulkdata/BILLSTATUS/114/hr/BILLSTATUS-114hr6277.xml"
}