<bill session="115" type="hc" number="147" updated="2019-04-18T15:52:57Z">
  <state datetime="2018-12-20">REFERRED</state>
  <status>
    <introduced datetime="2018-12-20"/>
  </status>
  <introduced datetime="2018-12-20"/>
  <titles>
    <title type="official" as="introduced">Calling for an update to certain Occupational Safety and Health Regulations and certain Environmental Protection Agency programs relating to highly hazardous chemicals.</title>
    <title type="display">Calling for an update to certain Occupational Safety and Health Regulations and certain Environmental Protection Agency programs relating to highly hazardous chemicals.</title>
  </titles>
  <sponsor bioguide_id="D000623"/>
  <cosponsors/>
  <actions>
    <action datetime="2018-12-20">
      <text>Introduced in House</text>
    </action>
    <action datetime="2018-12-20" state="REFERRED">
      <text>Referred to the Committee on Education and the Workforce, and in addition to the Committee on Energy and Commerce, for a period to be subsequently determined by the Speaker, in each case for consideration of such provisions as fall within the jurisdiction of the committee concerned.</text>
    </action>
    <action datetime="2018-12-20">
      <text>Referred to the Committee on Education and the Workforce, and in addition to the Committee on Energy and Commerce, for a period to be subsequently determined by the Speaker, in each case for consideration of such provisions as fall within the jurisdiction of the committee concerned.</text>
    </action>
  </actions>
  <committees>
    <committee subcommittee="" code="HSIF" name="House Energy and Commerce" activity="Referral"/>
    <committee subcommittee="" code="HSED" name="House Education and Labor" activity="Referral"/>
  </committees>
  <relatedbills/>
  <subjects>
    <term name="Labor and employment"/>
    <term name="Administrative law and regulatory procedures"/>
    <term name="Air quality"/>
    <term name="California"/>
    <term name="Department of Labor"/>
    <term name="Environmental Protection Agency (EPA)"/>
    <term name="Environmental regulatory procedures"/>
    <term name="Hazardous wastes and toxic substances"/>
    <term name="Industrial facilities"/>
    <term name="Oil and gas"/>
    <term name="Worker safety and health"/>
  </subjects>
  <amendments/>
  <summary date="2018-12-20T05:00:00Z" status="Introduced in House">Expresses the sense of Congress that: (1) the Occupational Safety and Health Administration should update regulations concerning refinery and chemical plant safety, and (2) the Environmental Protection Agency should update its Risk Management Plan rule pursuant to the Clean Air Act Amendments of 1990.</summary>
  <committee-reports/>
</bill>
