{
  "actions": [
    {
      "acted_at": "2018-07-16", 
      "action_code": "Intro-H", 
      "references": [], 
      "text": "Introduced in House", 
      "type": "action"
    }, 
    {
      "acted_at": "2018-07-16", 
      "action_code": "H11100", 
      "committees": [
        "HSGO"
      ], 
      "references": [], 
      "status": "REFERRED", 
      "text": "Referred to the Committee on Oversight and Government Reform, and in addition to the Committee on Veterans' Affairs, for a period to be subsequently determined by the Speaker, in each case for consideration of such provisions as fall within the jurisdiction of the committee concerned.", 
      "type": "referral"
    }, 
    {
      "acted_at": "2018-07-16", 
      "action_code": "H11100", 
      "committees": [
        "HSVR"
      ], 
      "references": [], 
      "text": "Referred to the Committee on Oversight and Government Reform, and in addition to the Committee on Veterans' Affairs, for a period to be subsequently determined by the Speaker, in each case for consideration of such provisions as fall within the jurisdiction of the committee concerned.", 
      "type": "referral"
    }, 
    {
      "acted_at": "2018-07-16", 
      "action_code": "", 
      "committees": [
        "HSVR"
      ], 
      "references": [], 
      "text": "Referred to the Subcommittee on Economic Opportunity.", 
      "type": "referral"
    }, 
    {
      "acted_at": "2018-07-17", 
      "action_code": "", 
      "committees": [
        "HSGO"
      ], 
      "references": [], 
      "text": "Committee Consideration and Mark-up Session Held.", 
      "type": "action"
    }, 
    {
      "acted_at": "2018-07-17", 
      "action_code": "", 
      "committees": [
        "HSGO"
      ], 
      "references": [], 
      "status": "REPORTED", 
      "text": "Ordered to be Reported by the Yeas and Nays: 20 - 12.", 
      "type": "calendar"
    }
  ], 
  "amendments": [], 
  "bill_id": "hr6391-115", 
  "bill_type": "hr", 
  "by_request": false, 
  "committee_reports": [], 
  "committees": [
    {
      "activity": [
        "markup", 
        "referral"
      ], 
      "committee": "House Oversight and Reform", 
      "committee_id": "HSGO"
    }, 
    {
      "activity": [
        "referral"
      ], 
      "committee": "House Veterans' Affairs", 
      "committee_id": "HSVR"
    }, 
    {
      "activity": [
        "referral"
      ], 
      "committee": "House Veterans' Affairs", 
      "committee_id": "HSVR", 
      "subcommittee": "Subcommittee on Economic Opportunity", 
      "subcommittee_id": "10"
    }
  ], 
  "congress": "115", 
  "cosponsors": [
    {
      "bioguide_id": "G000566", 
      "district": "4", 
      "name": "Gowdy, Trey", 
      "original_cosponsor": false, 
      "sponsored_at": "2018-09-07", 
      "state": "SC", 
      "title": "Rep", 
      "withdrawn_at": null
    }, 
    {
      "bioguide_id": "M001187", 
      "district": "11", 
      "name": "Meadows, Mark", 
      "original_cosponsor": true, 
      "sponsored_at": "2018-07-16", 
      "state": "NC", 
      "title": "Rep", 
      "withdrawn_at": null
    }, 
    {
      "bioguide_id": "M001201", 
      "district": "10", 
      "name": "Mitchell, Paul", 
      "original_cosponsor": true, 
      "sponsored_at": "2018-07-16", 
      "state": "MI", 
      "title": "Rep", 
      "withdrawn_at": null
    }
  ], 
  "enacted_as": null, 
  "history": {
    "active": true, 
    "active_at": "2018-07-17", 
    "awaiting_signature": false, 
    "enacted": false, 
    "vetoed": false
  }, 
  "introduced_at": "2018-07-16", 
  "number": "6391", 
  "official_title": "To reauthorize and modify the authority of the Merit Systems Protection Board, and for other purposes.", 
  "popular_title": null, 
  "related_bills": [], 
  "short_title": "Merit Systems Protection Board Reauthorization Act of 2018", 
  "sponsor": {
    "bioguide_id": "H001071", 
    "district": "10", 
    "name": "Hice, Jody B.", 
    "state": "GA", 
    "title": "Rep", 
    "type": "person"
  }, 
  "status": "REPORTED", 
  "status_at": "2018-07-17", 
  "subjects": [
    "Government operations and politics"
  ], 
  "subjects_top_term": "Government operations and politics", 
  "summary": null, 
  "titles": [
    {
      "as": "introduced", 
      "is_for_portion": false, 
      "title": "To reauthorize and modify the authority of the Merit Systems Protection Board, and for other purposes.", 
      "type": "official"
    }, 
    {
      "as": "introduced", 
      "is_for_portion": false, 
      "title": "Merit Systems Protection Board Reauthorization Act of 2018", 
      "type": "short"
    }, 
    {
      "as": "introduced", 
      "is_for_portion": false, 
      "title": "Merit Systems Protection Board Reauthorization Act of 2018", 
      "type": "short"
    }, 
    {
      "as": null, 
      "is_for_portion": false, 
      "title": "Merit Systems Protection Board Reauthorization Act of 2018", 
      "type": "display"
    }
  ], 
  "updated_at": "2019-04-18T16:26:06Z", 
  "url": "https://www.govinfo.gov/bulkdata/BILLSTATUS/115/hr/BILLSTATUS-115hr6391.xml"
}