{
  "actions": [
    {
      "acted_at": "2018-05-08", 
      "action_code": "Intro-H", 
      "references": [], 
      "text": "Introduced in House", 
      "type": "action"
    }, 
    {
      "acted_at": "2018-05-08", 
      "action_code": "H11100", 
      "committees": [
        "HSIF"
      ], 
      "references": [], 
      "status": "REFERRED", 
      "text": "Referred to the House Committee on Energy and Commerce.", 
      "type": "referral"
    }, 
    {
      "acted_at": "2018-05-11", 
      "action_code": "", 
      "committees": [
        "HSIF"
      ], 
      "references": [], 
      "text": "Referred to the Subcommittee on Communications and Technology.", 
      "type": "referral"
    }
  ], 
  "amendments": [], 
  "bill_id": "hr5700-115", 
  "bill_type": "hr", 
  "by_request": false, 
  "committee_reports": [], 
  "committees": [
    {
      "activity": [
        "referral"
      ], 
      "committee": "House Energy and Commerce", 
      "committee_id": "HSIF"
    }, 
    {
      "activity": [
        "referral"
      ], 
      "committee": "House Energy and Commerce", 
      "committee_id": "HSIF", 
      "subcommittee": "Subcommittee on Communications and Technology", 
      "subcommittee_id": "16"
    }
  ], 
  "congress": "115", 
  "cosponsors": [
    {
      "bioguide_id": "E000215", 
      "district": "18", 
      "name": "Eshoo, Anna G.", 
      "original_cosponsor": true, 
      "sponsored_at": "2018-05-08", 
      "state": "CA", 
      "title": "Rep", 
      "withdrawn_at": null
    }
  ], 
  "enacted_as": null, 
  "history": {
    "active": false, 
    "awaiting_signature": false, 
    "enacted": false, 
    "vetoed": false
  }, 
  "introduced_at": "2018-05-08", 
  "number": "5700", 
  "official_title": "To amend the Communications Act of 1934 to direct the Federal Communications Commission to designate a national dialing short code for users of mobile voice service to reach public safety personnel in critical, but non-emergency, circumstances.", 
  "popular_title": null, 
  "related_bills": [], 
  "short_title": "National Non-Emergency Mobile Number Act", 
  "sponsor": {
    "bioguide_id": "B001284", 
    "district": "5", 
    "name": "Brooks, Susan W.", 
    "state": "IN", 
    "title": "Rep", 
    "type": "person"
  }, 
  "status": "REFERRED", 
  "status_at": "2018-05-08", 
  "subjects": [
    "Science, technology, communications"
  ], 
  "subjects_top_term": "Science, technology, communications", 
  "summary": {
    "as": "Introduced in House", 
    "date": "2018-05-08T04:00:00Z", 
    "text": "National Non-Emergency Mobile Number Act\n\nThis bill amends the Communications Act of 1934 to require the Federal Communications Commission to designate a national dialing short code for users of mobile voice service to reach public safety personnel in critical, but non-emergency, circumstances. The FCC must consult with state departments of transportation, mobile voice service providers, and public safety representatives."
  }, 
  "titles": [
    {
      "as": "introduced", 
      "is_for_portion": false, 
      "title": "To amend the Communications Act of 1934 to direct the Federal Communications Commission to designate a national dialing short code for users of mobile voice service to reach public safety personnel in critical, but non-emergency, circumstances.", 
      "type": "official"
    }, 
    {
      "as": "introduced", 
      "is_for_portion": false, 
      "title": "National Non-Emergency Mobile Number Act", 
      "type": "short"
    }, 
    {
      "as": "introduced", 
      "is_for_portion": false, 
      "title": "National Non-Emergency Mobile Number Act", 
      "type": "short"
    }, 
    {
      "as": null, 
      "is_for_portion": false, 
      "title": "National Non-Emergency Mobile Number Act", 
      "type": "display"
    }
  ], 
  "updated_at": "2019-04-18T16:23:08Z", 
  "url": "https://www.govinfo.gov/bulkdata/BILLSTATUS/115/hr/BILLSTATUS-115hr5700.xml"
}