{
  "actions": [
    {
      "acted_at": "2014-02-04", 
      "action_code": "", 
      "links": [
        {
          "name": "S.Amdt.2634", 
          "url": "https://www.congress.gov/amendment/113th-congress/senate-amendment/2634"
        }, 
        {
          "name": "S737", 
          "url": "https://www.congress.gov/congressional-record/volume-160/senate-section/page/S737"
        }, 
        {
          "name": "SA 2633", 
          "url": "https://www.congress.gov/amendment/113th-congress/senate-amendment/2633"
        }, 
        {
          "name": "SA 2634", 
          "url": "https://www.congress.gov/amendment/113th-congress/senate-amendment/2634"
        }
      ], 
      "references": [
        {
          "reference": "CR S737", 
          "type": "consideration"
        }
      ], 
      "text": "SA 2634 fell when SA 2633 was withdrawn.", 
      "type": "action"
    }, 
    {
      "acted_at": "2014-02-04", 
      "action_code": "", 
      "links": [
        {
          "name": "S.Amdt.2634", 
          "url": "https://www.congress.gov/amendment/113th-congress/senate-amendment/2634"
        }, 
        {
          "name": "S737", 
          "url": "https://www.congress.gov/congressional-record/volume-160/senate-section/page/S737"
        }
      ], 
      "references": [
        {
          "reference": "CR S737", 
          "type": "consideration"
        }
      ], 
      "text": "Considered by Senate.", 
      "type": "action"
    }, 
    {
      "acted_at": "2014-01-14", 
      "action_code": "", 
      "links": [
        {
          "name": "S.Amdt.2634", 
          "url": "https://www.congress.gov/amendment/113th-congress/senate-amendment/2634"
        }, 
        {
          "name": "S300", 
          "url": "https://www.congress.gov/congressional-record/volume-160/senate-section/page/S300"
        }
      ], 
      "references": [
        {
          "reference": "CR S300", 
          "type": "consideration"
        }
      ], 
      "text": "Considered by Senate.", 
      "type": "action"
    }, 
    {
      "acted_at": "2014-01-13", 
      "action_code": "", 
      "links": [
        {
          "name": "S.Amdt.2634", 
          "url": "https://www.congress.gov/amendment/113th-congress/senate-amendment/2634"
        }, 
        {
          "name": "S268", 
          "url": "https://www.congress.gov/congressional-record/volume-160/senate-section/page/S268"
        }
      ], 
      "references": [
        {
          "reference": "CR S268", 
          "type": "consideration"
        }
      ], 
      "text": "Considered by Senate.", 
      "type": "action"
    }, 
    {
      "acted_at": "2014-01-09", 
      "action_code": "", 
      "links": [
        {
          "name": "S.Amdt.2634", 
          "url": "https://www.congress.gov/amendment/113th-congress/senate-amendment/2634"
        }, 
        {
          "name": "S204", 
          "url": "https://www.congress.gov/congressional-record/volume-160/senate-section/page/S204"
        }, 
        {
          "name": "SA 2633", 
          "url": "https://www.congress.gov/amendment/113th-congress/senate-amendment/2633"
        }, 
        {
          "name": "SA 2634", 
          "url": "https://www.congress.gov/amendment/113th-congress/senate-amendment/2634"
        }
      ], 
      "references": [
        {
          "reference": "CR S204", 
          "type": "consideration"
        }, 
        {
          "reference": "CR S204", 
          "type": "text"
        }
      ], 
      "text": "Amendment SA 2634 proposed by Senator Reid to Amendment SA 2633.", 
      "type": "action"
    }, 
    {
      "acted_at": "2014-01-09", 
      "action_code": "", 
      "references": [], 
      "text": "", 
      "type": "action"
    }, 
    {
      "acted_at": "2014-01-09", 
      "action_code": "93000", 
      "links": [
        {
          "name": "S.Amdt.2634", 
          "url": "https://www.congress.gov/amendment/113th-congress/senate-amendment/2634"
        }, 
        {
          "name": "S204", 
          "url": "https://www.congress.gov/congressional-record/volume-160/senate-section/page/S204"
        }, 
        {
          "name": "SA 2633", 
          "url": "https://www.congress.gov/amendment/113th-congress/senate-amendment/2633"
        }, 
        {
          "name": "SA 2634", 
          "url": "https://www.congress.gov/amendment/113th-congress/senate-amendment/2634"
        }
      ], 
      "references": [
        {
          "reference": "CR S204", 
          "type": "consideration"
        }, 
        {
          "reference": "CR S204", 
          "type": "text"
        }
      ], 
      "text": "Senate amendment proposed (on the floor): Amendment SA 2634 proposed by Senator Reid to Amendment SA 2633.", 
      "type": "action"
    }, 
    {
      "acted_at": "2014-01-09", 
      "action_code": "91000", 
      "references": [], 
      "text": "Senate amendment submitted", 
      "type": "action"
    }
  ], 
  "amendment_id": "samdt2634-113", 
  "amendment_type": "samdt", 
  "amends_amendment": {
    "amendment_id": "samdt2633-113", 
    "amendment_type": "samdt", 
    "congress": 113, 
    "description": null, 
    "number": 2633, 
    "purpose": "To change the enactment date."
  }, 
  "amends_bill": {
    "bill_id": "s1845-113", 
    "bill_type": "s", 
    "congress": 113, 
    "number": 1845
  }, 
  "amends_treaty": null, 
  "chamber": "s", 
  "congress": "113", 
  "description": null, 
  "introduced_at": "2014-01-09", 
  "number": 2634, 
  "proposed_at": "2014-01-09T05:00:00Z", 
  "purpose": "Of a perfecting nature.", 
  "sponsor": {
    "bioguide_id": "R000146", 
    "district": null, 
    "name": "Reid, Harry", 
    "state": "NV", 
    "title": "Sen", 
    "type": "person"
  }, 
  "status": "offered", 
  "status_at": "2014-01-09", 
  "updated_at": "2016-10-25T17:05:24Z"
}