{
  "actions": [
    {
      "acted_at": "2016-07-06", 
      "action_code": "Intro-H", 
      "references": [], 
      "text": "Introduced in House", 
      "type": "action"
    }, 
    {
      "acted_at": "2016-07-06", 
      "action_code": "H11100", 
      "committees": [
        "HSAS"
      ], 
      "references": [], 
      "status": "REFERRED", 
      "text": "Referred to the House Committee on Armed Services.", 
      "type": "referral"
    }, 
    {
      "acted_at": "2016-08-11", 
      "action_code": "", 
      "committees": [
        "HSAS"
      ], 
      "references": [], 
      "text": "Referred to the Subcommittee on Seapower and Projection Forces.", 
      "type": "referral"
    }
  ], 
  "amendments": [], 
  "bill_id": "hr5649-114", 
  "bill_type": "hr", 
  "by_request": false, 
  "committee_reports": [], 
  "committees": [
    {
      "activity": [
        "referral"
      ], 
      "committee": "House Armed Services", 
      "committee_id": "HSAS"
    }, 
    {
      "activity": [
        "referral"
      ], 
      "committee": "House Armed Services", 
      "committee_id": "HSAS", 
      "subcommittee": "Subcommittee on Seapower and Projection Forces", 
      "subcommittee_id": "28"
    }
  ], 
  "congress": "114", 
  "cosponsors": [
    {
      "bioguide_id": "H001071", 
      "district": "10", 
      "name": "Hice, Jody B.", 
      "original_cosponsor": true, 
      "sponsored_at": "2016-07-06", 
      "state": "GA", 
      "title": "Rep", 
      "withdrawn_at": null
    }
  ], 
  "enacted_as": null, 
  "history": {
    "active": false, 
    "awaiting_signature": false, 
    "enacted": false, 
    "vetoed": false
  }, 
  "introduced_at": "2016-07-06", 
  "number": "5649", 
  "official_title": "To amend title 10, United States Code, to prohibit any military aircraft provided for the use of the President from being used to transport a candidate for election for Federal office to a campaign event.", 
  "popular_title": null, 
  "related_bills": [], 
  "short_title": "Stop Abusing the Presidential Plane Act", 
  "sponsor": {
    "bioguide_id": "S001189", 
    "district": "8", 
    "name": "Scott, Austin", 
    "state": "GA", 
    "title": "Rep", 
    "type": "person"
  }, 
  "status": "REFERRED", 
  "status_at": "2016-07-06", 
  "subjects": [
    "Armed forces and national security", 
    "Aviation and airports", 
    "Elections, voting, political campaign regulation", 
    "Military facilities and property", 
    "Presidents and presidential powers, Vice Presidents"
  ], 
  "subjects_top_term": "Armed forces and national security", 
  "summary": {
    "as": "Introduced in House", 
    "date": "2016-07-06T04:00:00Z", 
    "text": "Stop Abusing the Presidential Plane Act\n\nThis bill prohibits an aircraft under the jurisdiction of a military department that is available for the President's use from being used to transport a candidate for federal office to an event promoting the candidate's election campaign.\n\nThis prohibition does not apply to the use of an aircraft to transport the President or Vice President to an event promoting the President's or Vice President's re-election campaign."
  }, 
  "titles": [
    {
      "as": "introduced", 
      "is_for_portion": false, 
      "title": "Stop Abusing the Presidential Plane Act", 
      "type": "short"
    }, 
    {
      "as": "introduced", 
      "is_for_portion": false, 
      "title": "To amend title 10, United States Code, to prohibit any military aircraft provided for the use of the President from being used to transport a candidate for election for Federal office to a campaign event.", 
      "type": "official"
    }, 
    {
      "as": null, 
      "is_for_portion": false, 
      "title": "Stop Abusing the Presidential Plane Act", 
      "type": "display"
    }
  ], 
  "updated_at": "2018-11-21T20:31:13Z", 
  "url": "https://www.govinfo.gov/bulkdata/BILLSTATUS/114/hr/BILLSTATUS-114hr5649.xml"
}