{
  "actions": [
    {
      "acted_at": "2017-10-31", 
      "action_code": "Intro-H", 
      "references": [], 
      "text": "Introduced in House", 
      "type": "action"
    }, 
    {
      "acted_at": "2017-10-31", 
      "action_code": "H11100", 
      "committees": [
        "HSGO"
      ], 
      "references": [], 
      "status": "REFERRED", 
      "text": "Referred to the House Committee on Oversight and Government Reform.", 
      "type": "referral"
    }
  ], 
  "amendments": [], 
  "bill_id": "hres598-115", 
  "bill_type": "hres", 
  "by_request": false, 
  "committee_reports": [], 
  "committees": [
    {
      "activity": [
        "referral"
      ], 
      "committee": "House Oversight and Reform", 
      "committee_id": "HSGO"
    }
  ], 
  "congress": "115", 
  "cosponsors": [], 
  "enacted_as": null, 
  "history": {
    "active": false, 
    "awaiting_signature": false, 
    "enacted": false, 
    "vetoed": false
  }, 
  "introduced_at": "2017-10-31", 
  "number": "598", 
  "official_title": "Recognizing the life and legacy of Isaac \"Ike\" Fulwood, Jr., Police Chief for the Metropolitan Police Department of the District of Columbia from 1989 to 1992.", 
  "popular_title": null, 
  "related_bills": [], 
  "short_title": null, 
  "sponsor": {
    "bioguide_id": "N000147", 
    "district": "0", 
    "name": "Norton, Eleanor Holmes", 
    "state": "DC", 
    "title": "Rep", 
    "type": "person"
  }, 
  "status": "REFERRED", 
  "status_at": "2017-10-31", 
  "subjects": [
    "Congressional tributes", 
    "Crime and law enforcement", 
    "District of Columbia", 
    "Law enforcement officers"
  ], 
  "subjects_top_term": "Crime and law enforcement", 
  "summary": {
    "as": "Introduced in House", 
    "date": "2017-10-31T04:00:00Z", 
    "text": "Honors the life and legacy of Isaac Fulwood, Jr., and acknowledges his contributions to the District of Columbia, to law enforcement, to community policing, and to creating a more peaceful and stable society."
  }, 
  "titles": [
    {
      "as": "introduced", 
      "is_for_portion": false, 
      "title": "Recognizing the life and legacy of Isaac \"Ike\" Fulwood, Jr., Police Chief for the Metropolitan Police Department of the District of Columbia from 1989 to 1992.", 
      "type": "official"
    }, 
    {
      "as": null, 
      "is_for_portion": false, 
      "title": "Recognizing the life and legacy of Isaac \"Ike\" Fulwood, Jr., Police Chief for the Metropolitan Police Department of the District of Columbia from 1989 to 1992.", 
      "type": "display"
    }
  ], 
  "updated_at": "2019-04-18T15:54:36Z", 
  "url": "https://www.govinfo.gov/bulkdata/BILLSTATUS/115/hres/BILLSTATUS-115hres598.xml"
}