{
  "actions": [
    {
      "acted_at": "2018-09-10", 
      "action_code": "Intro-H", 
      "references": [], 
      "text": "Introduced in House", 
      "type": "action"
    }, 
    {
      "acted_at": "2018-09-10", 
      "action_code": "", 
      "committees": [
        "HSVR"
      ], 
      "references": [], 
      "status": "REFERRED", 
      "text": "Referred to the Subcommittee on Economic Opportunity.", 
      "type": "referral"
    }, 
    {
      "acted_at": "2018-09-10", 
      "action_code": "H11100", 
      "committees": [
        "HSVR"
      ], 
      "references": [], 
      "text": "Referred to the Committee on Veterans' Affairs, and in addition to the Committee on Armed Services, for a period to be subsequently determined by the Speaker, in each case for consideration of such provisions as fall within the jurisdiction of the committee concerned.", 
      "type": "referral"
    }, 
    {
      "acted_at": "2018-09-10", 
      "action_code": "H11100", 
      "committees": [
        "HSAS"
      ], 
      "references": [], 
      "text": "Referred to the Committee on Veterans' Affairs, and in addition to the Committee on Armed Services, for a period to be subsequently determined by the Speaker, in each case for consideration of such provisions as fall within the jurisdiction of the committee concerned.", 
      "type": "referral"
    }, 
    {
      "acted_at": "2018-09-11", 
      "action_code": "", 
      "committees": [
        "HSAS"
      ], 
      "references": [], 
      "text": "Referred to the Subcommittee on Military Personnel.", 
      "type": "referral"
    }
  ], 
  "amendments": [], 
  "bill_id": "hr6766-115", 
  "bill_type": "hr", 
  "by_request": false, 
  "committee_reports": [], 
  "committees": [
    {
      "activity": [
        "referral"
      ], 
      "committee": "House Armed Services", 
      "committee_id": "HSAS"
    }, 
    {
      "activity": [
        "referral"
      ], 
      "committee": "House Armed Services", 
      "committee_id": "HSAS", 
      "subcommittee": "Subcommittee on Military Personnel", 
      "subcommittee_id": "02"
    }, 
    {
      "activity": [
        "referral"
      ], 
      "committee": "House Veterans' Affairs", 
      "committee_id": "HSVR"
    }, 
    {
      "activity": [
        "referral"
      ], 
      "committee": "House Veterans' Affairs", 
      "committee_id": "HSVR", 
      "subcommittee": "Subcommittee on Economic Opportunity", 
      "subcommittee_id": "10"
    }
  ], 
  "congress": "115", 
  "cosponsors": [
    {
      "bioguide_id": "B001298", 
      "district": "2", 
      "name": "Bacon, Don", 
      "original_cosponsor": true, 
      "sponsored_at": "2018-09-10", 
      "state": "NE", 
      "title": "Rep", 
      "withdrawn_at": null
    }, 
    {
      "bioguide_id": "S001201", 
      "district": "3", 
      "name": "Suozzi, Thomas R.", 
      "original_cosponsor": false, 
      "sponsored_at": "2018-09-13", 
      "state": "NY", 
      "title": "Rep", 
      "withdrawn_at": null
    }
  ], 
  "enacted_as": null, 
  "history": {
    "active": false, 
    "awaiting_signature": false, 
    "enacted": false, 
    "vetoed": false
  }, 
  "introduced_at": "2018-09-10", 
  "number": "6766", 
  "official_title": "To authorize the Secretary of Veterans Affairs to make grants to public institutions of higher education for the establishment of Veterans Resource Centers, and for other purposes.", 
  "popular_title": null, 
  "related_bills": [], 
  "short_title": "Veterans Resource Center Act of 2018", 
  "sponsor": {
    "bioguide_id": "P000613", 
    "district": "20", 
    "name": "Panetta, Jimmy", 
    "state": "CA", 
    "title": "Rep", 
    "type": "person"
  }, 
  "status": "REFERRED", 
  "status_at": "2018-09-10", 
  "subjects": [
    "Education"
  ], 
  "subjects_top_term": "Education", 
  "summary": null, 
  "titles": [
    {
      "as": "introduced", 
      "is_for_portion": false, 
      "title": "To authorize the Secretary of Veterans Affairs to make grants to public institutions of higher education for the establishment of Veterans Resource Centers, and for other purposes.", 
      "type": "official"
    }, 
    {
      "as": "introduced", 
      "is_for_portion": false, 
      "title": "Veterans Resource Center Act of 2018", 
      "type": "short"
    }, 
    {
      "as": "introduced", 
      "is_for_portion": false, 
      "title": "Veterans Resource Center Act of 2018", 
      "type": "short"
    }, 
    {
      "as": null, 
      "is_for_portion": false, 
      "title": "Veterans Resource Center Act of 2018", 
      "type": "display"
    }
  ], 
  "updated_at": "2019-04-18T16:27:17Z", 
  "url": "https://www.govinfo.gov/bulkdata/BILLSTATUS/115/hr/BILLSTATUS-115hr6766.xml"
}