{
  "actions": [
    {
      "acted_at": "2018-05-22", 
      "action_code": "10000", 
      "references": [], 
      "text": "Introduced in Senate", 
      "type": "action"
    }, 
    {
      "acted_at": "2018-05-22", 
      "action_code": "", 
      "committees": [
        "SSFI"
      ], 
      "references": [], 
      "status": "REFERRED", 
      "text": "Read twice and referred to the Committee on Finance.", 
      "type": "referral"
    }
  ], 
  "amendments": [], 
  "bill_id": "s2911-115", 
  "bill_type": "s", 
  "by_request": false, 
  "committee_reports": [], 
  "committees": [
    {
      "activity": [
        "referral"
      ], 
      "committee": "Senate Finance", 
      "committee_id": "SSFI"
    }
  ], 
  "congress": "115", 
  "cosponsors": [
    {
      "bioguide_id": "C001070", 
      "district": null, 
      "name": "Casey, Robert P., Jr.", 
      "original_cosponsor": true, 
      "sponsored_at": "2018-05-22", 
      "state": "PA", 
      "title": "Sen", 
      "withdrawn_at": null
    }, 
    {
      "bioguide_id": "C001056", 
      "district": null, 
      "name": "Cornyn, John", 
      "original_cosponsor": true, 
      "sponsored_at": "2018-05-22", 
      "state": "TX", 
      "title": "Sen", 
      "withdrawn_at": null
    }, 
    {
      "bioguide_id": "M001183", 
      "district": null, 
      "name": "Manchin, Joe, III", 
      "original_cosponsor": false, 
      "sponsored_at": "2018-09-12", 
      "state": "WV", 
      "title": "Sen", 
      "withdrawn_at": null
    }, 
    {
      "bioguide_id": "N000032", 
      "district": null, 
      "name": "Nelson, Bill", 
      "original_cosponsor": true, 
      "sponsored_at": "2018-05-22", 
      "state": "FL", 
      "title": "Sen", 
      "withdrawn_at": null
    }, 
    {
      "bioguide_id": "S000770", 
      "district": null, 
      "name": "Stabenow, Debbie", 
      "original_cosponsor": true, 
      "sponsored_at": "2018-05-22", 
      "state": "MI", 
      "title": "Sen", 
      "withdrawn_at": null
    }, 
    {
      "bioguide_id": "T000250", 
      "district": null, 
      "name": "Thune, John", 
      "original_cosponsor": true, 
      "sponsored_at": "2018-05-22", 
      "state": "SD", 
      "title": "Sen", 
      "withdrawn_at": null
    }
  ], 
  "enacted_as": null, 
  "history": {
    "active": false, 
    "awaiting_signature": false, 
    "enacted": false, 
    "vetoed": false
  }, 
  "introduced_at": "2018-05-22", 
  "number": "2911", 
  "official_title": "A bill to require the Secretary of Health and Human Services to provide guidance to States regarding Medicaid items and services for non-opioid pain treatment and management.", 
  "popular_title": null, 
  "related_bills": [
    {
      "bill_id": "s3120-115", 
      "identified_by": "CRS", 
      "reason": "related", 
      "type": "bill"
    }, 
    {
      "bill_id": "hr6-115", 
      "identified_by": "CRS", 
      "reason": "related", 
      "type": "bill"
    }
  ], 
  "short_title": "Enhancing Patient Access to Non-Opioid Treatment Options", 
  "sponsor": {
    "bioguide_id": "H001041", 
    "district": null, 
    "name": "Heller, Dean", 
    "state": "NV", 
    "title": "Sen", 
    "type": "person"
  }, 
  "status": "REFERRED", 
  "status_at": "2018-05-22", 
  "subjects": [
    "Administrative law and regulatory procedures", 
    "Alternative treatments", 
    "Department of Health and Human Services", 
    "Drug therapy", 
    "Government information and archives", 
    "Health", 
    "Medicaid"
  ], 
  "subjects_top_term": "Health", 
  "summary": {
    "as": "Introduced in Senate", 
    "date": "2018-05-22T04:00:00Z", 
    "text": "Enhancing Patient Access to Non-Opioid Treatment Options\n\nThis bill requires the Centers for Medicare & Medicaid Services to develop guidance for states on non-opioid treatments that may be provided under Medicaid."
  }, 
  "titles": [
    {
      "as": "introduced", 
      "is_for_portion": false, 
      "title": "A bill to require the Secretary of Health and Human Services to provide guidance to States regarding Medicaid items and services for non-opioid pain treatment and management.", 
      "type": "official"
    }, 
    {
      "as": "introduced", 
      "is_for_portion": false, 
      "title": "Enhancing Patient Access to Non-Opioid Treatment Options", 
      "type": "short"
    }, 
    {
      "as": "introduced", 
      "is_for_portion": false, 
      "title": "Enhancing Patient Access to Non-Opioid Treatment Options", 
      "type": "short"
    }, 
    {
      "as": null, 
      "is_for_portion": false, 
      "title": "Enhancing Patient Access to Non-Opioid Treatment Options", 
      "type": "display"
    }
  ], 
  "updated_at": "2019-04-18T16:43:24Z", 
  "url": "https://www.govinfo.gov/bulkdata/BILLSTATUS/115/s/BILLSTATUS-115s2911.xml"
}